CHANGELOG.txt
LICENCE.txt
MANIFEST.in
README.txt
setup.py
devtreeutil/__init__.py
devtreeutil.egg-info/PKG-INFO
devtreeutil.egg-info/SOURCES.txt
devtreeutil.egg-info/dependency_links.txt
devtreeutil.egg-info/requires.txt
devtreeutil.egg-info/top_level.txt