Metadata-Version: 2.1
Name: devtreeutil
Version: 0.0.4
Summary: devtreeutil is a library that makes simple actions a lot easier and more effective!
Home-page: UNKNOWN
Author: DevTree Studios
Author-email: devtreestudios@gmail.com
License: MIT
Keywords: devtreeutil
Platform: UNKNOWN
Classifier: Development Status :: 5 - Production/Stable
Classifier: Intended Audience :: Education
Classifier: Operating System :: Microsoft :: Windows :: Windows 10
Classifier: License :: OSI Approved :: MIT License
Classifier: Programming Language :: Python :: 3
License-File: LICENCE.txt
